tests/__init__.py
veil_aio_au/__init__.py
veil_aio_au/veil_au.py
veil_aio_au-0.1.4.dist-info/LICENSE
veil_aio_au-0.1.4.dist-info/METADATA
veil_aio_au-0.1.4.dist-info/WHEEL
veil_aio_au-0.1.4.dist-info/top_level.txt
veil_aio_au-0.1.4.dist-info/RECORD
