Metadata-Version: 2.1
Name: veil-aio-au
Version: 0.1.4
Summary: VeiL asyncio linux authentication utils.
Home-page: https://github.com/jsc-masshtab/veil-aio-au
Author: Aleksey Devyatkin
Author-email: a.devyatkin@mashtab.org
License: UNKNOWN
Platform: UNKNOWN
Classifier: Programming Language :: Python :: 3
Classifier: License :: OSI Approved :: MIT License
Classifier: Development Status :: 4 - Beta
Classifier: Operating System :: POSIX :: Linux
Requires-Python: >=3.5
Requires-Dist: python-pam (==1.8.*)
